evpn_connector/__init__.py
evpn_connector/version.py
evpn_connector/bgp/__init__.py
evpn_connector/bgp/client.py
evpn_connector/bgp/generated/__init__.py
evpn_connector/bgp/generated/attribute_pb2.py
evpn_connector/bgp/generated/attribute_pb2_grpc.py
evpn_connector/bgp/generated/capability_pb2.py
evpn_connector/bgp/generated/capability_pb2_grpc.py
evpn_connector/bgp/generated/gobgp_pb2.py
evpn_connector/bgp/generated/gobgp_pb2_grpc.py
evpn_connector/cmd/__init__.py
evpn_connector/cmd/evpn.py
evpn_connector/common/__init__.py
evpn_connector/common/conf_opts.py
evpn_connector/common/config.py
evpn_connector/common/constants.py
evpn_connector/common/log.py
evpn_connector/common/metrics.py
evpn_connector/common/sentry.py
evpn_connector/common/services/__init__.py
evpn_connector/common/services/softirq.py
evpn_connector/ovs/__init__.py
evpn_connector/ovs/client.py
evpn_connector/ovs/common.py
evpn_connector/ovs/shell.py
evpn_connector/service/__init__.py
evpn_connector/service/evpn.py
evpn_connector/service/objects.py
evpn_connector-2.2.0.data/data/share/evpn_connector/evpn_connector.cfg.sample
evpn_connector-2.2.0.dist-info/licenses/AUTHORS
evpn_connector-2.2.0.dist-info/licenses/LICENSE
evpn_connector-2.2.0.dist-info/METADATA
evpn_connector-2.2.0.dist-info/WHEEL
evpn_connector-2.2.0.dist-info/entry_points.txt
evpn_connector-2.2.0.dist-info/pbr.json
evpn_connector-2.2.0.dist-info/top_level.txt
evpn_connector-2.2.0.dist-info/RECORD
